pyhtcc/__init__.py
pyhtcc/__main__.py
pyhtcc/pyhtcc.py
pyhtcc-0.1.57.dist-info/METADATA
pyhtcc-0.1.57.dist-info/WHEEL
pyhtcc-0.1.57.dist-info/entry_points.txt
pyhtcc-0.1.57.dist-info/top_level.txt
pyhtcc-0.1.57.dist-info/RECORD
