Metadata-Version: 2.1
Name: pyhtcc
Version: 0.1.57
Home-page: http://github.com/csm10495/pyhtcc
Author: csm10495
Author-email: csm10495@gmail.com
License: MIT License
Classifier: Intended Audience :: Developers
Classifier: Natural Language :: English
Classifier: Operating System :: POSIX
Classifier: Operating System :: Microsoft :: Windows
Classifier: Programming Language :: Python
Classifier: Programming Language :: Python :: 3
Requires-Python: >=3.7
Requires-Dist: csmlog
Requires-Dist: requests>=2.27
Requires-Dist: deprecated
